tests/__init__.py
tests/test_square.py
zn/__init__.py
zn/square.py
zn-0.0.1.dist-info/LICENSE
zn-0.0.1.dist-info/METADATA
zn-0.0.1.dist-info/WHEEL
zn-0.0.1.dist-info/top_level.txt
zn-0.0.1.dist-info/RECORD
