Metadata-Version: 2.1
Name: zn
Version: 0.0.1
Summary: Zinc
Home-page: https://github.com/blinkdog/zn
Author: Patrick Meade
Author-email: blinkdog@protonmail.com
License: UNKNOWN
Platform: UNKNOWN
Classifier: Development Status :: 1 - Planning
Classifier: Intended Audience :: Developers
Classifier: License :: OSI Approved :: GNU Affero General Public License v3 or later (AGPLv3+)
Classifier: Operating System :: OS Independent
Classifier: Programming Language :: Python :: 3.7
Classifier: Topic :: Software Development :: Libraries :: Python Modules
Classifier: Topic :: Software Development :: Version Control
Classifier: Topic :: System :: Software Distribution
